identitylib/__init__.py
identitylib/api_client_mixin.py
identitylib/card_client/__init__.py
identitylib/card_client/api/__init__.py
identitylib/card_client/api/api_versions_api.py
identitylib/card_client/api/permissions_api.py
identitylib/card_client/api/v1beta1_api.py
identitylib/card_client/api_client.py
identitylib/card_client/api_response.py
identitylib/card_client/configuration.py
identitylib/card_client/exceptions.py
identitylib/card_client/models/__init__.py
identitylib/card_client/models/api_versions.py
identitylib/card_client/models/available_barcode.py
identitylib/card_client/models/available_barcode_batch_invalid.py
identitylib/card_client/models/available_barcode_batch_request.py
identitylib/card_client/models/available_barcode_batch_response_type.py
identitylib/card_client/models/available_barcode_request.py
identitylib/card_client/models/bad_request.py
identitylib/card_client/models/card.py
identitylib/card_client/models/card_bulk_update_element_request.py
identitylib/card_client/models/card_bulk_update_request.py
identitylib/card_client/models/card_bulk_update_response_type.py
identitylib/card_client/models/card_filter_request.py
identitylib/card_client/models/card_identifier.py
identitylib/card_client/models/card_identifier_allowed_actions.py
identitylib/card_client/models/card_identifier_bulk_update_details.py
identitylib/card_client/models/card_identifier_bulk_update_element_request.py
identitylib/card_client/models/card_identifier_bulk_update_request.py
identitylib/card_client/models/card_identifier_bulk_update_response_type.py
identitylib/card_client/models/card_identifier_destroy_response_type.py
identitylib/card_client/models/card_identifier_summary.py
identitylib/card_client/models/card_identifier_summary_request.py
identitylib/card_client/models/card_identifier_update_request.py
identitylib/card_client/models/card_identifier_update_response_type.py
identitylib/card_client/models/card_logo.py
identitylib/card_client/models/card_note.py
ucam_identitylib-3.4.0.dist-info/METADATA
ucam_identitylib-3.4.0.dist-info/WHEEL
ucam_identitylib-3.4.0.dist-info/RECORD
