Metadata-Version: 2.1
Name: ucam-identitylib
Version: 3.4.0
Summary: A module containing helpers and shared code related to identity systems within UIS, University of Cambridge.
Home-page: https://gitlab.developers.cam.ac.uk/uis/devops/iam/identity-lib
License: MIT
Author: University of Cambridge Information Services
Author-email: devops+ucam-identitylib@uis.cam.ac.uk
Requires-Python: >=3.9,<4.0
Classifier: Development Status :: 3 - Alpha
Classifier: Intended Audience :: Developers
Classifier: License :: OSI Approved :: MIT License
Classifier: Operating System :: OS Independent
Classifier: Programming Language :: Python :: 3
Classifier: Programming Language :: Python :: 3.9
Classifier: Programming Language :: Python :: 3.10
Classifier: Programming Language :: Python :: 3.11
Classifier: Programming Language :: Python :: 3.12
Classifier: Programming Language :: Python :: 3.13
Requires-Dist: aenum (>=3.1.15,<4.0.0)
Requires-Dist: frozendict (>=2.3.8,<3.0.0)
Requires-Dist: pydantic (>=2.6.1,<3.0.0)
Requires-Dist: python-dateutil (>=2.8.2,<3.0.0)
Requires-Dist: requests (>=2.31.0,<3.0.0)
Requires-Dist: typing-extensions (>=4.7.1,<5.0.0)
Requires-Dist: urllib3 (>=1.26,<3)
Project-URL: Repository, https://gitlab.developers.cam.ac.uk/uis/devops/iam/identity-lib
